pp.client_python-0.3.1-py2.7-nspkg.pth
pp/client/python/converter.py
pp/client/python/logger.py
pp/client/python/pdf.py
pp/client/python/poll.py
pp/client/python/unoconv.py
pp/client/python/util.py
pp/client/python/version.py
pp.client_python-0.3.1.data/scripts/pp-converters
pp.client_python-0.3.1.data/scripts/pp-pdf
pp.client_python-0.3.1.data/scripts/pp-poll
pp.client_python-0.3.1.data/scripts/pp-unoconv
pp.client_python-0.3.1.data/scripts/pp-version
pp.client_python-0.3.1.dist-info/DESCRIPTION.rst
pp.client_python-0.3.1.dist-info/entry_points.txt
pp.client_python-0.3.1.dist-info/METADATA
pp.client_python-0.3.1.dist-info/namespace_packages.txt
pp.client_python-0.3.1.dist-info/pydist.json
pp.client_python-0.3.1.dist-info/RECORD
pp.client_python-0.3.1.dist-info/top_level.txt
pp.client_python-0.3.1.dist-info/WHEEL
