Metadata-Version: 2.0
Name: pp.client-python
Version: 0.3.1
Summary: Produce & Publish Python Client
Home-page: http://pypi.python.org/pypi/pp.client-python
Author: Andreas Jung
Author-email: info@zopyx.com
License: UNKNOWN
Keywords: web pyramid pylons
Platform: UNKNOWN
Classifier: Programming Language :: Python :: 2.6
Classifier: Programming Language :: Python :: 2.7
Classifier: Programming Language :: Python :: 3.3
Classifier: Programming Language :: Python
Classifier: Framework :: Pyramid
Classifier: Topic :: Internet :: WWW/HTTP
Classifier: Topic :: Internet :: WWW/HTTP :: WSGI :: Application
Requires-Dist: setuptools
Requires-Dist: requests
Requires-Dist: logbook
Requires-Dist: plac
